[
  [
    {
      "pokemonName": "アーボ",
      "releaseDate": "2023-07-16T16:00:00Z",
      "rarity": 1,
      "sleepFaceName": "とぐろ寝",
      "energy": 0,
      "ID": 76,
      "np": 76000,
      "expCandy": 3,
      "researchExp": 11,
      "dreamShard": 26
    },
    {
      "pokemonName": "マンキー",
      "releaseDate": "2023-07-16T16:00:00Z",
      "rarity": 1,
      "sleepFaceName": "おこり寝",
      "energy": 0,
      "ID": 103,
      "np": 76000,
      "expCandy": 3,
      "researchExp": 11,
      "dreamShard": 26
    },
    {
      "pokemonName": "マダツボミ",
      "releaseDate": "2023-07-16T16:00:00Z",
      "rarity": 1,
      "sleepFaceName": "あしのばし寝",
      "energy": 0,
      "ID": 106,
      "np": 76000,
      "expCandy": 3,
      "researchExp": 13,
      "dreamShard": 23
    },
    {
      "pokemonName": "コダック",
      "releaseDate": "2023-07-16T16:00:00Z",
      "rarity": 1,
      "sleepFaceName": "ずつう寝",
      "energy": 0,
      "ID": 121,
      "np": 76000,
      "expCandy": 3,
      "researchExp": 13,
      "dreamShard": 23
    },
    {
      "pokemonName": "フシギダネ",
      "releaseDate": "2023-07-16T16:00:00Z",
      "rarity": 1,
      "sleepFaceName": "こうごうせい寝",
      "energy": 0,
      "ID": 16,
      "np": 418000,
      "expCandy": 3,
      "researchExp": 23,
      "dreamShard": 46
    },
    {
      "pokemonName": "チコリータ",
      "releaseDate": "2023-07-16T16:00:00Z",
      "rarity": 1,
      "sleepFaceName": "はっぱまわし寝",
      "energy": 0,
      "ID": 139,
      "np": 418000,
      "expCandy": 3,
      "researchExp": 23,
      "dreamShard": 46
    },
    {
      "pokemonName": "ミニリュウ",
      "releaseDate": "2024-01-24T07:00:00Z",
      "rarity": 1,
      "sleepFaceName": "とぐろ寝",
      "energy": 0,
      "ID": 472,
      "np": 570000,
      "expCandy": 3,
      "researchExp": 25,
      "dreamShard": 52
    },
    {
      "pokemonName": "ニャオハ",
      "releaseDate": "2024-07-15T07:00:00Z",
      "rarity": 1,
      "sleepFaceName": "こうばこずわり寝",
      "energy": 0,
      "ID": 534,
      "np": 950000,
      "expCandy": 3,
      "researchExp": 44,
      "dreamShard": 78
    },
    {
      "pokemonName": "アーボ",
      "releaseDate": "2023-07-16T16:00:00Z",
      "rarity": 2,
      "sleepFaceName": "のびちぢみ寝",
      "energy": 0,
      "ID": 77,
      "np": 1558000,
      "expCandy": 5,
      "researchExp": 63,
      "dreamShard": 158
    },
    {
      "pokemonName": "コダック",
      "releaseDate": "2023-07-16T16:00:00Z",
      "rarity": 2,
      "sleepFaceName": "おおあくび寝",
      "energy": 0,
      "ID": 122,
      "np": 1558000,
      "expCandy": 5,
      "researchExp": 76,
      "dreamShard": 135
    },
    {
      "pokemonName": "マダツボミ",
      "releaseDate": "2023-07-16T16:00:00Z",
      "rarity": 2,
      "sleepFaceName": "ようかいえき寝",
      "energy": 0,
      "ID": 107,
      "np": 1824000,
      "expCandy": 5,
      "researchExp": 87,
      "dreamShard": 155
    },
    {
      "pokemonName": "ウツドン",
      "releaseDate": "2023-07-16T16:00:00Z",
      "rarity": 1,
      "sleepFaceName": "ようかいえき寝",
      "energy": 0,
      "ID": 109,
      "np": 1824000,
      "expCandy": 5,
      "researchExp": 78,
      "dreamShard": 139
    },
    {
      "pokemonName": "マンキー",
      "releaseDate": "2023-07-16T16:00:00Z",
      "rarity": 2,
      "sleepFaceName": "ぼうだち寝",
      "energy": 0,
      "ID": 104,
      "np": 2090000,
      "expCandy": 5,
      "researchExp": 81,
      "dreamShard": 206
    },
    {
      "pokemonName": "フシギダネ",
      "releaseDate": "2023-07-16T16:00:00Z",
      "rarity": 2,
      "sleepFaceName": "ふんばり寝",
      "energy": 0,
      "ID": 17,
      "np": 2812000,
      "expCandy": 5,
      "researchExp": 122,
      "dreamShard": 255
    },
    {
      "pokemonName": "チコリータ",
      "releaseDate": "2023-07-16T16:00:00Z",
      "rarity": 2,
      "sleepFaceName": "はっぱたれ寝",
      "energy": 0,
      "ID": 140,
      "np": 2812000,
      "expCandy": 5,
      "researchExp": 122,
      "dreamShard": 255
    },
    {
      "pokemonName": "フシギソウ",
      "releaseDate": "2023-07-16T16:00:00Z",
      "rarity": 1,
      "sleepFaceName": "こうごうせい寝",
      "energy": 46326,
      "ID": 19,
      "np": 3154000,
      "expCandy": 5,
      "researchExp": 122,
      "dreamShard": 255
    },
    {
      "pokemonName": "ベイリーフ",
      "releaseDate": "2023-07-16T16:00:00Z",
      "rarity": 1,
      "sleepFaceName": "のび寝",
      "energy": 46326,
      "ID": 142,
      "np": 3154000,
      "expCandy": 5,
      "researchExp": 122,
      "dreamShard": 255
    },
    {
      "pokemonName": "オコリザル",
      "releaseDate": "2023-07-16T16:00:00Z",
      "rarity": 1,
      "sleepFaceName": "おこり寝",
      "energy": 46326,
      "ID": 181,
      "np": 3154000,
      "expCandy": 5,
      "researchExp": 122,
      "dreamShard": 255
    },
    {
      "pokemonName": "チルタリス",
      "releaseDate": "2023-07-16T16:00:00Z",
      "rarity": 1,
      "sleepFaceName": "はねうまり寝",
      "energy": 151061,
      "ID": 295,
      "np": 4256000,
      "expCandy": 5,
      "researchExp": 177,
      "dreamShard": 316
    },
    {
      "pokemonName": "ニャローテ",
      "releaseDate": "2024-07-15T07:00:00Z",
      "rarity": 1,
      "sleepFaceName": "まるまり寝",
      "energy": 151061,
      "ID": 538,
      "np": 4256000,
      "expCandy": 5,
      "researchExp": 197,
      "dreamShard": 279
    },
    {
      "pokemonName": "ハクリュー",
      "releaseDate": "2024-01-24T07:00:00Z",
      "rarity": 1,
      "sleepFaceName": "とぐろ寝",
      "energy": 151061,
      "ID": 476,
      "np": 4636000,
      "expCandy": 5,
      "researchExp": 177,
      "dreamShard": 370
    },
    {
      "pokemonName": "ウツドン",
      "releaseDate": "2023-07-16T16:00:00Z",
      "rarity": 2,
      "sleepFaceName": "ふゆう寝",
      "energy": 110779,
      "ID": 110,
      "np": 5054000,
      "expCandy": 7,
      "researchExp": 234,
      "dreamShard": 419
    },
    {
      "pokemonName": "アーボ",
      "releaseDate": "2023-07-16T16:00:00Z",
      "rarity": 3,
      "sleepFaceName": "ほぐれ寝",
      "energy": 110779,
      "ID": 78,
      "np": 6574000,
      "expCandy": 7,
      "researchExp": 284,
      "dreamShard": 729
    },
    {
      "pokemonName": "コダック",
      "releaseDate": "2023-07-16T16:00:00Z",
      "rarity": 3,
      "sleepFaceName": "やだやだ寝",
      "energy": 151061,
      "ID": 123,
      "np": 6574000,
      "expCandy": 7,
      "researchExp": 346,
      "dreamShard": 618
    },
    {
      "pokemonName": "マダツボミ",
      "releaseDate": "2023-07-16T16:00:00Z",
      "rarity": 3,
      "sleepFaceName": "ねをはる寝",
      "energy": 110779,
      "ID": 108,
      "np": 7144000,
      "expCandy": 7,
      "researchExp": 376,
      "dreamShard": 673
    },
    {
      "pokemonName": "マンキー",
      "releaseDate": "2023-07-16T16:00:00Z",
      "rarity": 3,
      "sleepFaceName": "おだやか寝",
      "energy": 110779,
      "ID": 105,
      "np": 7714000,
      "expCandy": 7,
      "researchExp": 333,
      "dreamShard": 855
    },
    {
      "pokemonName": "フシギソウ",
      "releaseDate": "2023-07-16T16:00:00Z",
      "rarity": 2,
      "sleepFaceName": "ふんばり寝",
      "energy": 203429,
      "ID": 20,
      "np": 7714000,
      "expCandy": 7,
      "researchExp": 327,
      "dreamShard": 686
    },
    {
      "pokemonName": "ベイリーフ",
      "releaseDate": "2023-07-16T16:00:00Z",
      "rarity": 2,
      "sleepFaceName": "つぼみふり寝",
      "energy": 203429,
      "ID": 143,
      "np": 7714000,
      "expCandy": 7,
      "researchExp": 327,
      "dreamShard": 686
    },
    {
      "pokemonName": "オコリザル",
      "releaseDate": "2023-07-16T16:00:00Z",
      "rarity": 2,
      "sleepFaceName": "じだんだ寝",
      "energy": 203429,
      "ID": 182,
      "np": 7714000,
      "expCandy": 7,
      "researchExp": 327,
      "dreamShard": 686
    },
    {
      "pokemonName": "アーボ",
      "releaseDate": "2023-07-16T16:00:00Z",
      "rarity": 4,
      "sleepFaceName": "おなかのうえ寝",
      "energy": 151061,
      "ID": 342,
      "np": 9120000,
      "expCandy": 8,
      "researchExp": 434,
      "dreamShard": 1115
    },
    {
      "pokemonName": "コダック",
      "releaseDate": "2023-07-16T16:00:00Z",
      "rarity": 4,
      "sleepFaceName": "おなかのうえ寝",
      "energy": 151061,
      "ID": 350,
      "np": 9120000,
      "expCandy": 8,
      "researchExp": 529,
      "dreamShard": 946
    },
    {
      "pokemonName": "フシギダネ",
      "releaseDate": "2023-07-16T16:00:00Z",
      "rarity": 3,
      "sleepFaceName": "ツルだし寝",
      "energy": 151061,
      "ID": 18,
      "np": 9918000,
      "expCandy": 7,
      "researchExp": 479,
      "dreamShard": 1005
    },
    {
      "pokemonName": "チコリータ",
      "releaseDate": "2023-07-16T16:00:00Z",
      "rarity": 3,
      "sleepFaceName": "へそてん寝",
      "energy": 151061,
      "ID": 141,
      "np": 9918000,
      "expCandy": 7,
      "researchExp": 479,
      "dreamShard": 1005
    },
    {
      "pokemonName": "マダツボミ",
      "releaseDate": "2023-07-16T16:00:00Z",
      "rarity": 4,
      "sleepFaceName": "おなかのうえ寝",
      "energy": 151061,
      "ID": 356,
      "np": 9918000,
      "expCandy": 8,
      "researchExp": 576,
      "dreamShard": 1032
    },
    {
      "pokemonName": "チルタリス",
      "releaseDate": "2023-07-16T16:00:00Z",
      "rarity": 2,
      "sleepFaceName": "はねやすめ寝",
      "energy": 423979,
      "ID": 296,
      "np": 9918000,
      "expCandy": 7,
      "researchExp": 455,
      "dreamShard": 816
    },
    {
      "pokemonName": "ウツボット",
      "releaseDate": "2023-07-16T16:00:00Z",
      "rarity": 1,
      "sleepFaceName": "ばふばふ寝",
      "energy": 511595,
      "ID": 187,
      "np": 9918000,
      "expCandy": 8,
      "researchExp": 407,
      "dreamShard": 729
    },
    {
      "pokemonName": "マンキー",
      "releaseDate": "2023-07-16T16:00:00Z",
      "rarity": 4,
      "sleepFaceName": "おなかのうえ寝",
      "energy": 151061,
      "ID": 352,
      "np": 10830000,
      "expCandy": 8,
      "researchExp": 516,
      "dreamShard": 1325
    },
    {
      "pokemonName": "ニャオハ",
      "releaseDate": "2024-07-15T07:00:00Z",
      "rarity": 2,
      "sleepFaceName": "ふみふみ寝",
      "energy": 75531,
      "ID": 535,
      "np": 11780000,
      "expCandy": 5,
      "researchExp": 539,
      "dreamShard": 967
    },
    {
      "pokemonName": "ミニリュウ",
      "releaseDate": "2024-01-24T07:00:00Z",
      "rarity": 2,
      "sleepFaceName": "くねく寝",
      "energy": 46326,
      "ID": 473,
      "np": 12692000,
      "expCandy": 5,
      "researchExp": 534,
      "dreamShard": 1122
    },
    {
      "pokemonName": "フシギダネ",
      "releaseDate": "2023-07-16T16:00:00Z",
      "rarity": 4,
      "sleepFaceName": "おなかのうえ寝",
      "energy": 151061,
      "ID": 328,
      "np": 13490000,
      "expCandy": 8,
      "researchExp": 720,
      "dreamShard": 1513
    },
    {
      "pokemonName": "チコリータ",
      "releaseDate": "2023-07-16T16:00:00Z",
      "rarity": 4,
      "sleepFaceName": "おなかのうえ寝",
      "energy": 151061,
      "ID": 379,
      "np": 13490000,
      "expCandy": 8,
      "researchExp": 720,
      "dreamShard": 1513
    },
    {
      "pokemonName": "リーフィア",
      "releaseDate": "2023-07-16T16:00:00Z",
      "rarity": 1,
      "sleepFaceName": "しっぽをふる寝",
      "energy": 810696,
      "ID": 268,
      "np": 13490000,
      "expCandy": 7,
      "researchExp": 453,
      "dreamShard": 1165
    },
    {
      "pokemonName": "フシギバナ",
      "releaseDate": "2023-07-16T16:00:00Z",
      "rarity": 1,
      "sleepFaceName": "こうごうせい寝",
      "energy": 810696,
      "ID": 64,
      "np": 14326000,
      "expCandy": 8,
      "researchExp": 587,
      "dreamShard": 1050
    },
    {
      "pokemonName": "メガニウム",
      "releaseDate": "2023-07-16T16:00:00Z",
      "rarity": 1,
      "sleepFaceName": "おだやか寝",
      "energy": 810696,
      "ID": 232,
      "np": 14326000,
      "expCandy": 8,
      "researchExp": 587,
      "dreamShard": 1050
    },
    {
      "pokemonName": "ハクリュー",
      "releaseDate": "2024-01-24T07:00:00Z",
      "rarity": 2,
      "sleepFaceName": "くねく寝",
      "energy": 423979,
      "ID": 477,
      "np": 15466000,
      "expCandy": 7,
      "researchExp": 651,
      "dreamShard": 1368
    },
    {
      "pokemonName": "ウツドン",
      "releaseDate": "2023-07-16T16:00:00Z",
      "rarity": 3,
      "sleepFaceName": "くっつき寝",
      "energy": 511595,
      "ID": 111,
      "np": 15466000,
      "expCandy": 9,
      "researchExp": 808,
      "dreamShard": 1447
    },
    {
      "pokemonName": "ニャローテ",
      "releaseDate": "2024-07-15T07:00:00Z",
      "rarity": 2,
      "sleepFaceName": "ぼうだち寝",
      "energy": 423979,
      "ID": 539,
      "np": 19570000,
      "expCandy": 7,
      "researchExp": 1001,
      "dreamShard": 1409
    },
    {
      "pokemonName": "ウツドン",
      "releaseDate": "2023-07-16T16:00:00Z",
      "rarity": 4,
      "sleepFaceName": "おなかのうえ寝",
      "energy": 151061,
      "ID": 357,
      "np": 20824000,
      "expCandy": 10,
      "researchExp": 1205,
      "dreamShard": 2157
    },
    {
      "pokemonName": "ミニリュウ",
      "releaseDate": "2024-01-24T07:00:00Z",
      "rarity": 3,
      "sleepFaceName": "ほぐれ寝",
      "energy": 342406,
      "ID": 474,
      "np": 20824000,
      "expCandy": 7,
      "researchExp": 1000,
      "dreamShard": 2100
    },
    {
      "pokemonName": "ウツボット",
      "releaseDate": "2023-07-16T16:00:00Z",
      "rarity": 2,
      "sleepFaceName": "つるささえ寝",
      "energy": 921725,
      "ID": 188,
      "np": 20824000,
      "expCandy": 10,
      "researchExp": 951,
      "dreamShard": 1703
    },
    {
      "pokemonName": "フシギソウ",
      "releaseDate": "2023-07-16T16:00:00Z",
      "rarity": 3,
      "sleepFaceName": "ツルだし寝",
      "energy": 704953,
      "ID": 21,
      "np": 22154000,
      "expCandy": 9,
      "researchExp": 1063,
      "dreamShard": 2234
    },
    {
      "pokemonName": "ベイリーフ",
      "releaseDate": "2023-07-16T16:00:00Z",
      "rarity": 3,
      "sleepFaceName": "かおりただよい寝",
      "energy": 704953,
      "ID": 144,
      "np": 22154000,
      "expCandy": 9,
      "researchExp": 1063,
      "dreamShard": 2234
    },
    {
      "pokemonName": "オコリザル",
      "releaseDate": "2023-07-16T16:00:00Z",
      "rarity": 3,
      "sleepFaceName": "おだやか寝",
      "energy": 704953,
      "ID": 183,
      "np": 22154000,
      "expCandy": 9,
      "researchExp": 1063,
      "dreamShard": 2234
    },
    {
      "pokemonName": "ミニリュウ",
      "releaseDate": "2024-01-24T07:00:00Z",
      "rarity": 4,
      "sleepFaceName": "おなかのうえ寝",
      "energy": 511595,
      "ID": 475,
      "np": 25536000,
      "expCandy": 8,
      "researchExp": 1359,
      "dreamShard": 2857
    },
    {
      "pokemonName": "チルタリス",
      "releaseDate": "2023-07-16T16:00:00Z",
      "rarity": 3,
      "sleepFaceName": "わたぐも寝",
      "energy": 1038306,
      "ID": 297,
      "np": 27132000,
      "expCandy": 9,
      "researchExp": 1414,
      "dreamShard": 2532
    },
    {
      "pokemonName": "マスカーニャ",
      "releaseDate": "2024-07-15T07:00:00Z",
      "rarity": 1,
      "sleepFaceName": "まるまり寝",
      "energy": 1038306,
      "ID": 542,
      "np": 27132000,
      "expCandy": 8,
      "researchExp": 1238,
      "dreamShard": 1742
    },
    {
      "pokemonName": "リーフィア",
      "releaseDate": "2023-07-16T16:00:00Z",
      "rarity": 2,
      "sleepFaceName": "ふんばり寝",
      "energy": 1289248,
      "ID": 269,
      "np": 27132000,
      "expCandy": 9,
      "researchExp": 1015,
      "dreamShard": 2614
    },
    {
      "pokemonName": "ベイリーフ",
      "releaseDate": "2023-07-16T16:00:00Z",
      "rarity": 4,
      "sleepFaceName": "おなかのうえ寝",
      "energy": 266875,
      "ID": 380,
      "np": 28766000,
      "expCandy": 10,
      "researchExp": 1530,
      "dreamShard": 3216
    },
    {
      "pokemonName": "フシギソウ",
      "releaseDate": "2023-07-16T16:00:00Z",
      "rarity": 4,
      "sleepFaceName": "おなかのうえ寝",
      "energy": 511595,
      "ID": 329,
      "np": 28766000,
      "expCandy": 10,
      "researchExp": 1530,
      "dreamShard": 3216
    },
    {
      "pokemonName": "オコリザル",
      "releaseDate": "2023-07-16T16:00:00Z",
      "rarity": 4,
      "sleepFaceName": "おなかのうえ寝",
      "energy": 511595,
      "ID": 353,
      "np": 28766000,
      "expCandy": 10,
      "researchExp": 1530,
      "dreamShard": 3216
    },
    {
      "pokemonName": "フシギバナ",
      "releaseDate": "2023-07-16T16:00:00Z",
      "rarity": 2,
      "sleepFaceName": "ふんばり寝",
      "energy": 1289248,
      "ID": 65,
      "np": 28766000,
      "expCandy": 10,
      "researchExp": 1312,
      "dreamShard": 2351
    },
    {
      "pokemonName": "メガニウム",
      "releaseDate": "2023-07-16T16:00:00Z",
      "rarity": 2,
      "sleepFaceName": "くびふり寝",
      "energy": 1289248,
      "ID": 233,
      "np": 28766000,
      "expCandy": 10,
      "researchExp": 1312,
      "dreamShard": 2351
    },
    {
      "pokemonName": "ニャオハ",
      "releaseDate": "2024-07-15T07:00:00Z",
      "rarity": 3,
      "sleepFaceName": "へそてん寝",
      "energy": 423979,
      "ID": 536,
      "np": 33478000,
      "expCandy": 7,
      "researchExp": 1741,
      "dreamShard": 3127
    },
    {
      "pokemonName": "チルタリス",
      "releaseDate": "2023-07-16T16:00:00Z",
      "rarity": 4,
      "sleepFaceName": "おなかのうえ寝",
      "energy": 511595,
      "ID": 413,
      "np": 33478000,
      "expCandy": 10,
      "researchExp": 1934,
      "dreamShard": 3463
    },
    {
      "pokemonName": "ニャオハ",
      "releaseDate": "2024-07-15T07:00:00Z",
      "rarity": 4,
      "sleepFaceName": "おなかのうえ寝",
      "energy": 511595,
      "ID": 537,
      "np": 38304000,
      "expCandy": 8,
      "researchExp": 2209,
      "dreamShard": 3967
    },
    {
      "pokemonName": "ハクリュー",
      "releaseDate": "2024-01-24T07:00:00Z",
      "rarity": 3,
      "sleepFaceName": "ほぐれ寝",
      "energy": 1038306,
      "ID": 478,
      "np": 38304000,
      "expCandy": 9,
      "researchExp": 1835,
      "dreamShard": 3858
    },
    {
      "pokemonName": "カイリュー",
      "releaseDate": "2024-01-24T07:00:00Z",
      "rarity": 1,
      "sleepFaceName": "まるまり寝",
      "energy": 1741777,
      "ID": 480,
      "np": 46208000,
      "expCandy": 8,
      "researchExp": 1880,
      "dreamShard": 3366
    },
    {
      "pokemonName": "ハクリュー",
      "releaseDate": "2024-01-24T07:00:00Z",
      "rarity": 4,
      "sleepFaceName": "おなかのうえ寝",
      "energy": 1038306,
      "ID": 479,
      "np": 48070000,
      "expCandy": 10,
      "researchExp": 2554,
      "dreamShard": 5368
    },
    {
      "pokemonName": "ウツボット",
      "releaseDate": "2023-07-16T16:00:00Z",
      "rarity": 3,
      "sleepFaceName": "ひっくりかえり寝",
      "energy": 1741777,
      "ID": 189,
      "np": 48070000,
      "expCandy": 12,
      "researchExp": 2502,
      "dreamShard": 4481
    },
    {
      "pokemonName": "ニャローテ",
      "releaseDate": "2024-07-15T07:00:00Z",
      "rarity": 3,
      "sleepFaceName": "じゃれつく寝",
      "energy": 1038306,
      "ID": 540,
      "np": 52706000,
      "expCandy": 9,
      "researchExp": 3073,
      "dreamShard": 4321
    },
    {
      "pokemonName": "マスカーニャ",
      "releaseDate": "2024-07-15T07:00:00Z",
      "rarity": 2,
      "sleepFaceName": "おじぎ寝",
      "energy": 1582395,
      "ID": 543,
      "np": 52706000,
      "expCandy": 10,
      "researchExp": 2689,
      "dreamShard": 3781
    },
    {
      "pokemonName": "ウツボット",
      "releaseDate": "2023-07-16T16:00:00Z",
      "rarity": 4,
      "sleepFaceName": "おなかのうえ寝",
      "energy": 1038306,
      "ID": 358,
      "np": 59052000,
      "expCandy": 13,
      "researchExp": 3408,
      "dreamShard": 6105
    },
    {
      "pokemonName": "リーフィア",
      "releaseDate": "2023-07-16T16:00:00Z",
      "rarity": 3,
      "sleepFaceName": "はっぱつかみ寝",
      "energy": 2276921,
      "ID": 270,
      "np": 59052000,
      "expCandy": 11,
      "researchExp": 2520,
      "dreamShard": 6493
    },
    {
      "pokemonName": "フシギバナ",
      "releaseDate": "2023-07-16T16:00:00Z",
      "rarity": 3,
      "sleepFaceName": "ツルだし寝",
      "energy": 2276921,
      "ID": 66,
      "np": 62776000,
      "expCandy": 12,
      "researchExp": 3266,
      "dreamShard": 5850
    },
    {
      "pokemonName": "メガニウム",
      "releaseDate": "2023-07-16T16:00:00Z",
      "rarity": 3,
      "sleepFaceName": "はながさいた寝",
      "energy": 2276921,
      "ID": 234,
      "np": 62776000,
      "expCandy": 12,
      "researchExp": 3266,
      "dreamShard": 5850
    },
    {
      "pokemonName": "ニャローテ",
      "releaseDate": "2024-07-15T07:00:00Z",
      "rarity": 4,
      "sleepFaceName": "おなかのうえ寝",
      "energy": 1038306,
      "ID": 541,
      "np": 65702000,
      "expCandy": 10,
      "researchExp": 4248,
      "dreamShard": 5973
    },
    {
      "pokemonName": "リーフィア",
      "releaseDate": "2023-07-16T16:00:00Z",
      "rarity": 4,
      "sleepFaceName": "おなかのうえ寝",
      "energy": 1431702,
      "ID": 425,
      "np": 73112000,
      "expCandy": 12,
      "researchExp": 3461,
      "dreamShard": 8917
    },
    {
      "pokemonName": "フシギバナ",
      "releaseDate": "2023-07-16T16:00:00Z",
      "rarity": 4,
      "sleepFaceName": "おなかのうえ寝",
      "energy": 1431702,
      "ID": 330,
      "np": 77102000,
      "expCandy": 13,
      "researchExp": 4449,
      "dreamShard": 7968
    },
    {
      "pokemonName": "メガニウム",
      "releaseDate": "2023-07-16T16:00:00Z",
      "rarity": 4,
      "sleepFaceName": "おなかのうえ寝",
      "energy": 1431702,
      "ID": 381,
      "np": 77102000,
      "expCandy": 13,
      "researchExp": 4449,
      "dreamShard": 7968
    },
    {
      "pokemonName": "カイリュー",
      "releaseDate": "2024-01-24T07:00:00Z",
      "rarity": 2,
      "sleepFaceName": "すわり寝",
      "energy": 2476059,
      "ID": 481,
      "np": 77102000,
      "expCandy": 10,
      "researchExp": 3510,
      "dreamShard": 6286
    },
    {
      "pokemonName": "マスカーニャ",
      "releaseDate": "2024-07-15T07:00:00Z",
      "rarity": 3,
      "sleepFaceName": "マジシャン寝",
      "energy": 2686523,
      "ID": 544,
      "np": 139612000,
      "expCandy": 12,
      "researchExp": 8133,
      "dreamShard": 11434
    },
    {
      "pokemonName": "カイリュー",
      "releaseDate": "2024-01-24T07:00:00Z",
      "rarity": 3,
      "sleepFaceName": "おなかだし寝",
      "energy": 4086475,
      "ID": 482,
      "np": 155344000,
      "expCandy": 12,
      "researchExp": 8079,
      "dreamShard": 14470
    },
    {
      "pokemonName": "マスカーニャ",
      "releaseDate": "2024-07-15T07:00:00Z",
      "rarity": 4,
      "sleepFaceName": "おなかのうえ寝",
      "energy": 1741777,
      "ID": 545,
      "np": 163742000,
      "expCandy": 13,
      "researchExp": 10588,
      "dreamShard": 14884
    },
    {
      "pokemonName": "カイリュー",
      "releaseDate": "2024-01-24T07:00:00Z",
      "rarity": 4,
      "sleepFaceName": "おなかのうえ寝",
      "energy": 2686523,
      "ID": 483,
      "np": 185516000,
      "expCandy": 13,
      "researchExp": 10700,
      "dreamShard": 19165
    }
  ],
  [
    {
      "pokemonName": "ピカチュウ",
      "releaseDate": "2023-07-16T16:00:00Z",
      "rarity": 1,
      "sleepFaceName": "まるまり寝",
      "energy": 0,
      "ID": 1,
      "np": 76000,
      "expCandy": 4,
      "researchExp": 11,
      "dreamShard": 27
    },
    {
      "pokemonName": "ニャース",
      "releaseDate": "2023-07-16T16:00:00Z",
      "rarity": 1,
      "sleepFaceName": "まるまり寝",
      "energy": 0,
      "ID": 10,
      "np": 76000,
      "expCandy": 3,
      "researchExp": 12,
      "dreamShard": 24
    },
    {
      "pokemonName": "ヤドン",
      "releaseDate": "2023-07-16T16:00:00Z",
      "rarity": 1,
      "sleepFaceName": "ぐでぐで寝",
      "energy": 0,
      "ID": 46,
      "np": 76000,
      "expCandy": 3,
      "researchExp": 15,
      "dreamShard": 19
    },
    {
      "pokemonName": "プリン",
      "releaseDate": "2023-07-16T16:00:00Z",
      "rarity": 1,
      "sleepFaceName": "すわり寝",
      "energy": 0,
      "ID": 31,
      "np": 304000,
      "expCandy": 4,
      "researchExp": 27,
      "dreamShard": 31
    },
    {
      "pokemonName": "ラルトス",
      "releaseDate": "2024-01-24T07:00:00Z",
      "rarity": 1,
      "sleepFaceName": "つっぷし寝",
      "energy": 0,
      "ID": 484,
      "np": 304000,
      "expCandy": 3,
      "researchExp": 21,
      "dreamShard": 42
    },
    {
      "pokemonName": "イーブイ",
      "releaseDate": "2023-07-16T16:00:00Z",
      "rarity": 1,
      "sleepFaceName": "まるまり寝",
      "energy": 0,
      "ID": 4,
      "np": 418000,
      "expCandy": 3,
      "researchExp": 24,
      "dreamShard": 43
    },
    {
      "pokemonName": "ソーナンス",
      "releaseDate": "2023-07-16T16:00:00Z",
      "rarity": 1,
      "sleepFaceName": "しっぽかくし寝",
      "energy": 0,
      "ID": 148,
      "np": 570000,
      "expCandy": 4,
      "researchExp": 33,
      "dreamShard": 38
    },
    {
      "pokemonName": "ムンナ",
      "releaseDate": "2025-03-17T01:00:00Z",
      "rarity": 1,
      "sleepFaceName": "ゆめのけむり寝",
      "energy": 0,
      "ID": 672,
      "np": 570000,
      "expCandy": 3,
      "researchExp": 35,
      "dreamShard": 35
    },
    {
      "pokemonName": "ピッピ",
      "releaseDate": "2023-09-27T20:00:00Z",
      "rarity": 1,
      "sleepFaceName": "おだやか寝",
      "energy": 0,
      "ID": 440,
      "np": 950000,
      "expCandy": 4,
      "researchExp": 53,
      "dreamShard": 60
    },
    {
      "pokemonName": "ヤドン",
      "releaseDate": "2023-07-16T16:00:00Z",
      "rarity": 2,
      "sleepFaceName": "ぼーっと寝",
      "energy": 0,
      "ID": 47,
      "np": 2090000,
      "expCandy": 5,
      "researchExp": 122,
      "dreamShard": 133
    },
    {
      "pokemonName": "トゲチック",
      "releaseDate": "2023-07-16T16:00:00Z",
      "rarity": 1,
      "sleepFaceName": "すわりはばたき寝",
      "energy": 46326,
      "ID": 241,
      "np": 2090000,
      "expCandy": 4,
      "researchExp": 82,
      "dreamShard": 170
    },
    {
      "pokemonName": "ピカチュウ",
      "releaseDate": "2023-07-16T16:00:00Z",
      "rarity": 2,
      "sleepFaceName": "たれみみ寝",
      "energy": 0,
      "ID": 2,
      "np": 2280000,
      "expCandy": 6,
      "researchExp": 82,
      "dreamShard": 242
    },
    {
      "pokemonName": "ニャース",
      "releaseDate": "2023-07-16T16:00:00Z",
      "rarity": 2,
      "sleepFaceName": "すわり寝",
      "energy": 0,
      "ID": 11,
      "np": 2280000,
      "expCandy": 5,
      "researchExp": 100,
      "dreamShard": 210
    },
    {
      "pokemonName": "プリン",
      "releaseDate": "2023-07-16T16:00:00Z",
      "rarity": 2,
      "sleepFaceName": "ぼんやり寝",
      "energy": 20142,
      "ID": 32,
      "np": 2508000,
      "expCandy": 6,
      "researchExp": 148,
      "dreamShard": 161
    },
    {
      "pokemonName": "イーブイ",
      "releaseDate": "2023-07-16T16:00:00Z",
      "rarity": 2,
      "sleepFaceName": "たれみみ寝",
      "energy": 20142,
      "ID": 5,
      "np": 2812000,
      "expCandy": 5,
      "researchExp": 132,
      "dreamShard": 237
    },
    {
      "pokemonName": "ソーナンス",
      "releaseDate": "2023-07-16T16:00:00Z",
      "rarity": 2,
      "sleepFaceName": "がまん寝",
      "energy": 20142,
      "ID": 149,
      "np": 3154000,
      "expCandy": 6,
      "researchExp": 183,
      "dreamShard": 200
    },
    {
      "pokemonName": "ヤドラン",
      "releaseDate": "2023-07-16T16:00:00Z",
      "rarity": 1,
      "sleepFaceName": "なかよし寝",
      "energy": 110779,
      "ID": 124,
      "np": 3154000,
      "expCandy": 5,
      "researchExp": 142,
      "dreamShard": 218
    },
    {
      "pokemonName": "ペルシアン",
      "releaseDate": "2023-07-16T16:00:00Z",
      "rarity": 1,
      "sleepFaceName": "ゆうが寝",
      "energy": 110779,
      "ID": 175,
      "np": 3154000,
      "expCandy": 5,
      "researchExp": 122,
      "dreamShard": 255
    },
    {
      "pokemonName": "ピッピ",
      "releaseDate": "2023-09-27T20:00:00Z",
      "rarity": 2,
      "sleepFaceName": "こっくり寝",
      "energy": 20142,
      "ID": 441,
      "np": 3914000,
      "expCandy": 6,
      "researchExp": 226,
      "dreamShard": 245
    },
    {
      "pokemonName": "キルリア",
      "releaseDate": "2024-01-24T07:00:00Z",
      "rarity": 1,
      "sleepFaceName": "すわりおじぎ寝",
      "energy": 110779,
      "ID": 488,
      "np": 4636000,
      "expCandy": 5,
      "researchExp": 177,
      "dreamShard": 370
    },
    {
      "pokemonName": "メタモン",
      "releaseDate": "2023-07-16T16:00:00Z",
      "rarity": 1,
      "sleepFaceName": "いしにへんしん寝",
      "energy": 75531,
      "ID": 211,
      "np": 5472000,
      "expCandy": 6,
      "researchExp": 226,
      "dreamShard": 405
    },
    {
      "pokemonName": "トゲチック",
      "releaseDate": "2023-07-16T16:00:00Z",
      "rarity": 2,
      "sleepFaceName": "たちはばたき寝",
      "energy": 203429,
      "ID": 242,
      "np": 5472000,
      "expCandy": 6,
      "researchExp": 233,
      "dreamShard": 488
    },
    {
      "pokemonName": "ムンナ",
      "releaseDate": "2025-03-17T01:00:00Z",
      "rarity": 2,
      "sleepFaceName": "ふゆうころころ寝",
      "energy": 75531,
      "ID": 673,
      "np": 6004000,
      "expCandy": 5,
      "researchExp": 366,
      "dreamShard": 337
    },
    {
      "pokemonName": "デデンネ",
      "releaseDate": "2024-03-11T07:00:00Z",
      "rarity": 1,
      "sleepFaceName": "しっぽまるまり寝",
      "energy": 151061,
      "ID": 508,
      "np": 7144000,
      "expCandy": 6,
      "researchExp": 294,
      "dreamShard": 527
    },
    {
      "pokemonName": "ヤドン",
      "releaseDate": "2023-07-16T16:00:00Z",
      "rarity": 3,
      "sleepFaceName": "まぬけだ寝",
      "energy": 151061,
      "ID": 48,
      "np": 7714000,
      "expCandy": 7,
      "researchExp": 506,
      "dreamShard": 546
    },
    {
      "pokemonName": "キュワワー",
      "releaseDate": "2024-04-22T07:00:00Z",
      "rarity": 1,
      "sleepFaceName": "はなすりすり寝",
      "energy": 203429,
      "ID": 515,
      "np": 7714000,
      "expCandy": 6,
      "researchExp": 239,
      "dreamShard": 709
    },
    {
      "pokemonName": "ヤドラン",
      "releaseDate": "2023-07-16T16:00:00Z",
      "rarity": 2,
      "sleepFaceName": "よだれ寝",
      "energy": 342406,
      "ID": 125,
      "np": 7714000,
      "expCandy": 7,
      "researchExp": 383,
      "dreamShard": 586
    },
    {
      "pokemonName": "ペルシアン",
      "releaseDate": "2023-07-16T16:00:00Z",
      "rarity": 2,
      "sleepFaceName": "ふんばり寝",
      "energy": 342406,
      "ID": 176,
      "np": 7714000,
      "expCandy": 7,
      "researchExp": 327,
      "dreamShard": 686
    },
    {
      "pokemonName": "ニャース",
      "releaseDate": "2023-07-16T16:00:00Z",
      "rarity": 3,
      "sleepFaceName": "ネコにこばん寝",
      "energy": 151061,
      "ID": 12,
      "np": 8322000,
      "expCandy": 7,
      "researchExp": 402,
      "dreamShard": 843
    },
    {
      "pokemonName": "ピカチュウ",
      "releaseDate": "2023-07-16T16:00:00Z",
      "rarity": 3,
      "sleepFaceName": "ほうでん寝",
      "energy": 203429,
      "ID": 3,
      "np": 8322000,
      "expCandy": 8,
      "researchExp": 328,
      "dreamShard": 975
    },
    {
      "pokemonName": "プリン",
      "releaseDate": "2023-07-16T16:00:00Z",
      "rarity": 3,
      "sleepFaceName": "うたう寝",
      "energy": 266875,
      "ID": 33,
      "np": 9120000,
      "expCandy": 8,
      "researchExp": 595,
      "dreamShard": 642
    },
    {
      "pokemonName": "イーブイ",
      "releaseDate": "2023-07-16T16:00:00Z",
      "rarity": 3,
      "sleepFaceName": "げんきいっぱい寝",
      "energy": 266875,
      "ID": 6,
      "np": 9918000,
      "expCandy": 7,
      "researchExp": 520,
      "dreamShard": 931
    },
    {
      "pokemonName": "ラルトス",
      "releaseDate": "2024-01-24T07:00:00Z",
      "rarity": 2,
      "sleepFaceName": "もじもじ寝",
      "energy": 20142,
      "ID": 485,
      "np": 10830000,
      "expCandy": 5,
      "researchExp": 457,
      "dreamShard": 959
    },
    {
      "pokemonName": "ソーナンス",
      "releaseDate": "2023-07-16T16:00:00Z",
      "rarity": 3,
      "sleepFaceName": "きめポーズ寝",
      "energy": 266875,
      "ID": 150,
      "np": 10830000,
      "expCandy": 8,
      "researchExp": 707,
      "dreamShard": 762
    },
    {
      "pokemonName": "ヤドン",
      "releaseDate": "2023-07-16T16:00:00Z",
      "rarity": 4,
      "sleepFaceName": "おなかのうえ寝",
      "energy": 511595,
      "ID": 362,
      "np": 10830000,
      "expCandy": 8,
      "researchExp": 784,
      "dreamShard": 845
    },
    {
      "pokemonName": "ピカチュウ",
      "releaseDate": "2023-07-16T16:00:00Z",
      "rarity": 4,
      "sleepFaceName": "おなかのうえ寝",
      "energy": 151061,
      "ID": 344,
      "np": 11780000,
      "expCandy": 9,
      "researchExp": 513,
      "dreamShard": 1527
    },
    {
      "pokemonName": "ニャース",
      "releaseDate": "2023-07-16T16:00:00Z",
      "rarity": 4,
      "sleepFaceName": "おなかのうえ寝",
      "energy": 151061,
      "ID": 348,
      "np": 11780000,
      "expCandy": 8,
      "researchExp": 629,
      "dreamShard": 1320
    },
    {
      "pokemonName": "プリン",
      "releaseDate": "2023-07-16T16:00:00Z",
      "rarity": 4,
      "sleepFaceName": "おなかのうえ寝",
      "energy": 151061,
      "ID": 346,
      "np": 12692000,
      "expCandy": 9,
      "researchExp": 917,
      "dreamShard": 989
    },
    {
      "pokemonName": "メタモン",
      "releaseDate": "2023-07-16T16:00:00Z",
      "rarity": 2,
      "sleepFaceName": "そのまま寝",
      "energy": 266875,
      "ID": 212,
      "np": 12692000,
      "expCandy": 8,
      "researchExp": 580,
      "dreamShard": 1040
    },
    {
      "pokemonName": "ピッピ",
      "releaseDate": "2023-09-27T20:00:00Z",
      "rarity": 3,
      "sleepFaceName": "ゆびをふる寝",
      "energy": 266875,
      "ID": 442,
      "np": 12692000,
      "expCandy": 8,
      "researchExp": 827,
      "dreamShard": 892
    },
    {
      "pokemonName": "イーブイ",
      "releaseDate": "2023-07-16T16:00:00Z",
      "rarity": 4,
      "sleepFaceName": "おなかのうえ寝",
      "energy": 151061,
      "ID": 372,
      "np": 13490000,
      "expCandy": 8,
      "researchExp": 782,
      "dreamShard": 1401
    },
    {
      "pokemonName": "エーフィ",
      "releaseDate": "2023-07-16T16:00:00Z",
      "rarity": 1,
      "sleepFaceName": "よち寝",
      "energy": 810696,
      "ID": 247,
      "np": 13490000,
      "expCandy": 7,
      "researchExp": 453,
      "dreamShard": 1165
    },
    {
      "pokemonName": "ソーナンス",
      "releaseDate": "2023-07-16T16:00:00Z",
      "rarity": 4,
      "sleepFaceName": "おなかのうえ寝",
      "energy": 511595,
      "ID": 399,
      "np": 14326000,
      "expCandy": 9,
      "researchExp": 1038,
      "dreamShard": 1118
    },
    {
      "pokemonName": "ピクシー",
      "releaseDate": "2023-09-27T20:00:00Z",
      "rarity": 1,
      "sleepFaceName": "おだやか寝",
      "energy": 604246,
      "ID": 444,
      "np": 14326000,
      "expCandy": 8,
      "researchExp": 691,
      "dreamShard": 863
    },
    {
      "pokemonName": "キルリア",
      "releaseDate": "2024-01-24T07:00:00Z",
      "rarity": 2,
      "sleepFaceName": "レヴェランス寝",
      "energy": 342406,
      "ID": 489,
      "np": 15466000,
      "expCandy": 7,
      "researchExp": 651,
      "dreamShard": 1368
    },
    {
      "pokemonName": "ピッピ",
      "releaseDate": "2023-09-27T20:00:00Z",
      "rarity": 4,
      "sleepFaceName": "おなかのうえ寝",
      "energy": 511595,
      "ID": 443,
      "np": 16644000,
      "expCandy": 9,
      "researchExp": 1204,
      "dreamShard": 1297
    },
    {
      "pokemonName": "トゲチック",
      "releaseDate": "2023-07-16T16:00:00Z",
      "rarity": 3,
      "sleepFaceName": "うかびぱたぱた寝",
      "energy": 704953,
      "ID": 243,
      "np": 16644000,
      "expCandy": 8,
      "researchExp": 800,
      "dreamShard": 1681
    },
    {
      "pokemonName": "ラルトス",
      "releaseDate": "2024-01-24T07:00:00Z",
      "rarity": 3,
      "sleepFaceName": "にこにこ寝",
      "energy": 266875,
      "ID": 486,
      "np": 18050000,
      "expCandy": 7,
      "researchExp": 867,
      "dreamShard": 1822
    },
    {
      "pokemonName": "ムンナ",
      "releaseDate": "2025-03-17T01:00:00Z",
      "rarity": 3,
      "sleepFaceName": "ゆめくい寝",
      "energy": 423979,
      "ID": 674,
      "np": 18050000,
      "expCandy": 7,
      "researchExp": 1247,
      "dreamShard": 1141
    },
    {
      "pokemonName": "サーナイト",
      "releaseDate": "2024-01-24T07:00:00Z",
      "rarity": 1,
      "sleepFaceName": "すそゆらし寝",
      "energy": 1038306,
      "ID": 492,
      "np": 20824000,
      "expCandy": 8,
      "researchExp": 697,
      "dreamShard": 1794
    },
    {
      "pokemonName": "ラルトス",
      "releaseDate": "2024-01-24T07:00:00Z",
      "rarity": 4,
      "sleepFaceName": "おなかのうえ寝",
      "energy": 151061,
      "ID": 487,
      "np": 22154000,
      "expCandy": 8,
      "researchExp": 1179,
      "dreamShard": 2478
    },
    {
      "pokemonName": "トゲチック",
      "releaseDate": "2023-07-16T16:00:00Z",
      "rarity": 4,
      "sleepFaceName": "おなかのうえ寝",
      "energy": 266875,
      "ID": 391,
      "np": 22154000,
      "expCandy": 9,
      "researchExp": 1179,
      "dreamShard": 2478
    },
    {
      "pokemonName": "ヤドラン",
      "releaseDate": "2023-07-16T16:00:00Z",
      "rarity": 3,
      "sleepFaceName": "しっぽかまれ寝",
      "energy": 921725,
      "ID": 126,
      "np": 22154000,
      "expCandy": 9,
      "researchExp": 1247,
      "dreamShard": 1904
    },
    {
      "pokemonName": "ペルシアン",
      "releaseDate": "2023-07-16T16:00:00Z",
      "rarity": 3,
      "sleepFaceName": "ごめん寝",
      "energy": 921725,
      "ID": 177,
      "np": 22154000,
      "expCandy": 9,
      "researchExp": 1063,
      "dreamShard": 2234
    },
    {
      "pokemonName": "ムシャーナ",
      "releaseDate": "2025-03-17T01:00:00Z",
      "rarity": 1,
      "sleepFaceName": "ふゆうすりすり寝",
      "energy": 1038306,
      "ID": 675,
      "np": 22154000,
      "expCandy": 7,
      "researchExp": 1196,
      "dreamShard": 1094
    },
    {
      "pokemonName": "デデンネ",
      "releaseDate": "2024-03-11T07:00:00Z",
      "rarity": 2,
      "sleepFaceName": "かおごしごし寝",
      "energy": 423979,
      "ID": 509,
      "np": 25536000,
      "expCandy": 8,
      "researchExp": 1166,
      "dreamShard": 2088
    },
    {
      "pokemonName": "キュワワー",
      "releaseDate": "2024-04-22T07:00:00Z",
      "rarity": 2,
      "sleepFaceName": "こっくりふゆう寝",
      "energy": 511595,
      "ID": 516,
      "np": 27132000,
      "expCandy": 8,
      "researchExp": 929,
      "dreamShard": 2769
    },
    {
      "pokemonName": "エーフィ",
      "releaseDate": "2023-07-16T16:00:00Z",
      "rarity": 2,
      "sleepFaceName": "おすわり寝",
      "energy": 1289248,
      "ID": 248,
      "np": 27132000,
      "expCandy": 9,
      "researchExp": 1015,
      "dreamShard": 2614
    },
    {
      "pokemonName": "ペルシアン",
      "releaseDate": "2023-07-16T16:00:00Z",
      "rarity": 4,
      "sleepFaceName": "おなかのうえ寝",
      "energy": 511595,
      "ID": 349,
      "np": 28766000,
      "expCandy": 10,
      "researchExp": 1530,
      "dreamShard": 3216
    },
    {
      "pokemonName": "ヤドラン",
      "releaseDate": "2023-07-16T16:00:00Z",
      "rarity": 4,
      "sleepFaceName": "おなかのうえ寝",
      "energy": 511595,
      "ID": 363,
      "np": 28766000,
      "expCandy": 10,
      "researchExp": 1796,
      "dreamShard": 2741
    },
    {
      "pokemonName": "ピクシー",
      "releaseDate": "2023-09-27T20:00:00Z",
      "rarity": 2,
      "sleepFaceName": "こっくり寝",
      "energy": 1038306,
      "ID": 445,
      "np": 28766000,
      "expCandy": 10,
      "researchExp": 1548,
      "dreamShard": 1929
    },
    {
      "pokemonName": "メタモン",
      "releaseDate": "2023-07-16T16:00:00Z",
      "rarity": 3,
      "sleepFaceName": "ピカチュウ寝",
      "energy": 810696,
      "ID": 213,
      "np": 31806000,
      "expCandy": 10,
      "researchExp": 1657,
      "dreamShard": 2968
    },
    {
      "pokemonName": "キルリア",
      "releaseDate": "2024-01-24T07:00:00Z",
      "rarity": 3,
      "sleepFaceName": "おどりながら寝",
      "energy": 921725,
      "ID": 490,
      "np": 38304000,
      "expCandy": 9,
      "researchExp": 1835,
      "dreamShard": 3858
    },
    {
      "pokemonName": "サーナイト",
      "releaseDate": "2024-01-24T07:00:00Z",
      "rarity": 2,
      "sleepFaceName": "はずかしい寝",
      "energy": 1582395,
      "ID": 493,
      "np": 38304000,
      "expCandy": 10,
      "researchExp": 1432,
      "dreamShard": 3688
    },
    {
      "pokemonName": "メタモン",
      "releaseDate": "2023-07-16T16:00:00Z",
      "rarity": 4,
      "sleepFaceName": "カイリュー寝",
      "energy": 342406,
      "ID": 327,
      "np": 40926000,
      "expCandy": 11,
      "researchExp": 2363,
      "dreamShard": 4234
    },
    {
      "pokemonName": "メタモン",
      "releaseDate": "2023-07-16T16:00:00Z",
      "rarity": 4,
      "sleepFaceName": "おなかのうえ寝",
      "energy": 342406,
      "ID": 371,
      "np": 40926000,
      "expCandy": 11,
      "researchExp": 2363,
      "dreamShard": 4234
    },
    {
      "pokemonName": "キルリア",
      "releaseDate": "2024-01-24T07:00:00Z",
      "rarity": 4,
      "sleepFaceName": "おなかのうえ寝",
      "energy": 511595,
      "ID": 491,
      "np": 48070000,
      "expCandy": 10,
      "researchExp": 2554,
      "dreamShard": 5368
    },
    {
      "pokemonName": "デデンネ",
      "releaseDate": "2024-03-11T07:00:00Z",
      "rarity": 3,
      "sleepFaceName": "ほっぺすりすり寝",
      "energy": 1038306,
      "ID": 510,
      "np": 55594000,
      "expCandy": 10,
      "researchExp": 2892,
      "dreamShard": 5179
    },
    {
      "pokemonName": "キュワワー",
      "releaseDate": "2024-04-22T07:00:00Z",
      "rarity": 3,
      "sleepFaceName": "はなウェーブ寝",
      "energy": 1160717,
      "ID": 517,
      "np": 59052000,
      "expCandy": 10,
      "researchExp": 2306,
      "dreamShard": 6878
    },
    {
      "pokemonName": "ムシャーナ",
      "releaseDate": "2025-03-17T01:00:00Z",
      "rarity": 2,
      "sleepFaceName": "かおごしごし寝",
      "energy": 1582395,
      "ID": 676,
      "np": 59052000,
      "expCandy": 9,
      "researchExp": 3562,
      "dreamShard": 3254
    },
    {
      "pokemonName": "エーフィ",
      "releaseDate": "2023-07-16T16:00:00Z",
      "rarity": 3,
      "sleepFaceName": "へそてん寝",
      "energy": 2276921,
      "ID": 249,
      "np": 59052000,
      "expCandy": 11,
      "researchExp": 2520,
      "dreamShard": 6493
    },
    {
      "pokemonName": "ピクシー",
      "releaseDate": "2023-09-27T20:00:00Z",
      "rarity": 3,
      "sleepFaceName": "ゆびをふる寝",
      "energy": 1910321,
      "ID": 446,
      "np": 62776000,
      "expCandy": 12,
      "researchExp": 3854,
      "dreamShard": 4799
    },
    {
      "pokemonName": "デデンネ",
      "releaseDate": "2024-03-11T07:00:00Z",
      "rarity": 4,
      "sleepFaceName": "おなかのうえ寝",
      "energy": 511595,
      "ID": 511,
      "np": 68666000,
      "expCandy": 11,
      "researchExp": 3963,
      "dreamShard": 7099
    },
    {
      "pokemonName": "キュワワー",
      "releaseDate": "2024-04-22T07:00:00Z",
      "rarity": 4,
      "sleepFaceName": "おなかのうえ寝",
      "energy": 1038306,
      "ID": 518,
      "np": 73112000,
      "expCandy": 11,
      "researchExp": 3166,
      "dreamShard": 9446
    },
    {
      "pokemonName": "エーフィ",
      "releaseDate": "2023-07-16T16:00:00Z",
      "rarity": 4,
      "sleepFaceName": "おなかのうえ寝",
      "energy": 1431702,
      "ID": 396,
      "np": 73112000,
      "expCandy": 12,
      "researchExp": 3461,
      "dreamShard": 8917
    },
    {
      "pokemonName": "ピクシー",
      "releaseDate": "2023-09-27T20:00:00Z",
      "rarity": 4,
      "sleepFaceName": "おなかのうえ寝",
      "energy": 1741777,
      "ID": 447,
      "np": 77102000,
      "expCandy": 13,
      "researchExp": 5249,
      "dreamShard": 6535
    },
    {
      "pokemonName": "サーナイト",
      "releaseDate": "2024-01-24T07:00:00Z",
      "rarity": 3,
      "sleepFaceName": "すそひろがり寝",
      "energy": 2686523,
      "ID": 494,
      "np": 81244000,
      "expCandy": 12,
      "researchExp": 3466,
      "dreamShard": 8931
    },
    {
      "pokemonName": "サーナイト",
      "releaseDate": "2024-01-24T07:00:00Z",
      "rarity": 4,
      "sleepFaceName": "おなかのうえ寝",
      "energy": 1741777,
      "ID": 495,
      "np": 97356000,
      "expCandy": 13,
      "researchExp": 4607,
      "dreamShard": 11872
    }
  ],
  [
    {
      "pokemonName": "ピチュー",
      "releaseDate": "2023-07-16T16:00:00Z",
      "rarity": 1,
      "sleepFaceName": "おだやか寝",
      "energy": 0,
      "ID": 13,
      "np": 76000,
      "expCandy": 3,
      "researchExp": 11,
      "dreamShard": 27
    },
    {
      "pokemonName": "ププリン",
      "releaseDate": "2023-07-16T16:00:00Z",
      "rarity": 1,
      "sleepFaceName": "はずみ寝",
      "energy": 0,
      "ID": 112,
      "np": 76000,
      "expCandy": 3,
      "researchExp": 15,
      "dreamShard": 19
    },
    {
      "pokemonName": "ドードー",
      "releaseDate": "2023-07-16T16:00:00Z",
      "rarity": 1,
      "sleepFaceName": "みはり寝",
      "energy": 0,
      "ID": 127,
      "np": 76000,
      "expCandy": 3,
      "researchExp": 11,
      "dreamShard": 27
    },
    {
      "pokemonName": "チルット",
      "releaseDate": "2023-07-16T16:00:00Z",
      "rarity": 1,
      "sleepFaceName": "はねやすめ寝",
      "energy": 0,
      "ID": 157,
      "np": 76000,
      "expCandy": 3,
      "researchExp": 12,
      "dreamShard": 24
    },
    {
      "pokemonName": "ソーナノ",
      "releaseDate": "2023-07-16T16:00:00Z",
      "rarity": 1,
      "sleepFaceName": "しっぽもどし寝",
      "energy": 0,
      "ID": 160,
      "np": 76000,
      "expCandy": 3,
      "researchExp": 15,
      "dreamShard": 19
    },
    {
      "pokemonName": "リオル",
      "releaseDate": "2023-07-16T16:00:00Z",
      "rarity": 1,
      "sleepFaceName": "ひざかかえ寝",
      "energy": 0,
      "ID": 298,
      "np": 76000,
      "expCandy": 3,
      "researchExp": 12,
      "dreamShard": 24
    },
    {
      "pokemonName": "ゼニガメ",
      "releaseDate": "2023-07-16T16:00:00Z",
      "rarity": 1,
      "sleepFaceName": "からにこもる寝",
      "energy": 0,
      "ID": 34,
      "np": 418000,
      "expCandy": 3,
      "researchExp": 23,
      "dreamShard": 46
    },
    {
      "pokemonName": "トゲピー",
      "releaseDate": "2023-07-16T16:00:00Z",
      "rarity": 1,
      "sleepFaceName": "ころころ寝",
      "energy": 0,
      "ID": 67,
      "np": 418000,
      "expCandy": 3,
      "researchExp": 23,
      "dreamShard": 46
    },
    {
      "pokemonName": "ピィ",
      "releaseDate": "2023-09-27T20:00:00Z",
      "rarity": 1,
      "sleepFaceName": "ころころ寝",
      "energy": 0,
      "ID": 436,
      "np": 418000,
      "expCandy": 3,
      "researchExp": 29,
      "dreamShard": 34
    },
    {
      "pokemonName": "ウソッキー",
      "releaseDate": "2023-07-16T16:00:00Z",
      "rarity": 1,
      "sleepFaceName": "きのふり寝",
      "energy": 0,
      "ID": 118,
      "np": 570000,
      "expCandy": 4,
      "researchExp": 27,
      "dreamShard": 48
    },
    {
      "pokemonName": "ヌイコグマ",
      "releaseDate": "2024-01-24T07:00:00Z",
      "rarity": 1,
      "sleepFaceName": "じたばた寝",
      "energy": 0,
      "ID": 500,
      "np": 570000,
      "expCandy": 3,
      "researchExp": 32,
      "dreamShard": 41
    },
    {
      "pokemonName": "クワッス",
      "releaseDate": "2024-07-15T07:00:00Z",
      "rarity": 1,
      "sleepFaceName": "すわり寝",
      "energy": 0,
      "ID": 558,
      "np": 950000,
      "expCandy": 3,
      "researchExp": 48,
      "dreamShard": 70
    },
    {
      "pokemonName": "ピチュー",
      "releaseDate": "2023-07-16T16:00:00Z",
      "rarity": 2,
      "sleepFaceName": "すわり寝",
      "energy": 0,
      "ID": 14,
      "np": 1558000,
      "expCandy": 5,
      "researchExp": 58,
      "dreamShard": 167
    },
    {
      "pokemonName": "ププリン",
      "releaseDate": "2023-07-16T16:00:00Z",
      "rarity": 2,
      "sleepFaceName": "ぼんやり寝",
      "energy": 0,
      "ID": 113,
      "np": 1558000,
      "expCandy": 5,
      "researchExp": 94,
      "dreamShard": 103
    },
    {
      "pokemonName": "ドードー",
      "releaseDate": "2023-07-16T16:00:00Z",
      "rarity": 2,
      "sleepFaceName": "みはりさぼり寝",
      "energy": 0,
      "ID": 128,
      "np": 1558000,
      "expCandy": 5,
      "researchExp": 58,
      "dreamShard": 167
    },
    {
      "pokemonName": "ソーナノ",
      "releaseDate": "2023-07-16T16:00:00Z",
      "rarity": 2,
      "sleepFaceName": "がまん寝",
      "energy": 0,
      "ID": 161,
      "np": 1558000,
      "expCandy": 5,
      "researchExp": 94,
      "dreamShard": 103
    },
    {
      "pokemonName": "チルット",
      "releaseDate": "2023-07-16T16:00:00Z",
      "rarity": 2,
      "sleepFaceName": "ぱたぱた寝",
      "energy": 0,
      "ID": 158,
      "np": 1824000,
      "expCandy": 5,
      "researchExp": 80,
      "dreamShard": 167
    },
    {
      "pokemonName": "ドードリオ",
      "releaseDate": "2023-07-16T16:00:00Z",
      "rarity": 1,
      "sleepFaceName": "みはり寝",
      "energy": 75531,
      "ID": 199,
      "np": 1824000,
      "expCandy": 5,
      "researchExp": 65,
      "dreamShard": 163
    },
    {
      "pokemonName": "リオル",
      "releaseDate": "2023-07-16T16:00:00Z",
      "rarity": 2,
      "sleepFaceName": "しゅぎょうちゅう寝",
      "energy": 0,
      "ID": 299,
      "np": 2280000,
      "expCandy": 5,
      "researchExp": 100,
      "dreamShard": 210
    },
    {
      "pokemonName": "ゼニガメ",
      "releaseDate": "2023-07-16T16:00:00Z",
      "rarity": 2,
      "sleepFaceName": "こもらない寝",
      "energy": 0,
      "ID": 35,
      "np": 2812000,
      "expCandy": 5,
      "researchExp": 122,
      "dreamShard": 255
    },
    {
      "pokemonName": "トゲピー",
      "releaseDate": "2023-07-16T16:00:00Z",
      "rarity": 2,
      "sleepFaceName": "ひっくりかえり寝",
      "energy": 0,
      "ID": 68,
      "np": 2812000,
      "expCandy": 5,
      "researchExp": 122,
      "dreamShard": 255
    },
    {
      "pokemonName": "ピィ",
      "releaseDate": "2023-09-27T20:00:00Z",
      "rarity": 2,
      "sleepFaceName": "こっくり寝",
      "energy": 0,
      "ID": 437,
      "np": 2812000,
      "expCandy": 5,
      "researchExp": 165,
      "dreamShard": 179
    },
    {
      "pokemonName": "ウソッキー",
      "releaseDate": "2023-07-16T16:00:00Z",
      "rarity": 2,
      "sleepFaceName": "きのふりさぼり寝",
      "energy": 0,
      "ID": 119,
      "np": 3154000,
      "expCandy": 6,
      "researchExp": 147,
      "dreamShard": 264
    },
    {
      "pokemonName": "カメール",
      "releaseDate": "2023-07-16T16:00:00Z",
      "rarity": 1,
      "sleepFaceName": "からにこもる寝",
      "energy": 46326,
      "ID": 37,
      "np": 3154000,
      "expCandy": 5,
      "researchExp": 122,
      "dreamShard": 255
    },
    {
      "pokemonName": "ウェルカモ",
      "releaseDate": "2024-07-15T07:00:00Z",
      "rarity": 1,
      "sleepFaceName": "かたひざたて寝",
      "energy": 151061,
      "ID": 562,
      "np": 4256000,
      "expCandy": 5,
      "researchExp": 196,
      "dreamShard": 281
    },
    {
      "pokemonName": "ドードリオ",
      "releaseDate": "2023-07-16T16:00:00Z",
      "rarity": 2,
      "sleepFaceName": "みはりさぼり寝",
      "energy": 266875,
      "ID": 200,
      "np": 5054000,
      "expCandy": 7,
      "researchExp": 192,
      "dreamShard": 493
    },
    {
      "pokemonName": "キテルグマ",
      "releaseDate": "2024-01-24T07:00:00Z",
      "rarity": 1,
      "sleepFaceName": "すわり寝",
      "energy": 423979,
      "ID": 504,
      "np": 6004000,
      "expCandy": 5,
      "researchExp": 309,
      "dreamShard": 334
    },
    {
      "pokemonName": "ピチュー",
      "releaseDate": "2023-07-16T16:00:00Z",
      "rarity": 3,
      "sleepFaceName": "ほうでん寝",
      "energy": 110779,
      "ID": 15,
      "np": 6574000,
      "expCandy": 7,
      "researchExp": 260,
      "dreamShard": 771
    },
    {
      "pokemonName": "ププリン",
      "releaseDate": "2023-07-16T16:00:00Z",
      "rarity": 3,
      "sleepFaceName": "うたう寝",
      "energy": 110779,
      "ID": 114,
      "np": 6574000,
      "expCandy": 7,
      "researchExp": 431,
      "dreamShard": 466
    },
    {
      "pokemonName": "ドードー",
      "releaseDate": "2023-07-16T16:00:00Z",
      "rarity": 3,
      "sleepFaceName": "ふたご寝",
      "energy": 110779,
      "ID": 129,
      "np": 6574000,
      "expCandy": 7,
      "researchExp": 260,
      "dreamShard": 771
    },
    {
      "pokemonName": "ソーナノ",
      "releaseDate": "2023-07-16T16:00:00Z",
      "rarity": 3,
      "sleepFaceName": "きめポーズ寝",
      "energy": 110779,
      "ID": 162,
      "np": 6574000,
      "expCandy": 7,
      "researchExp": 431,
      "dreamShard": 466
    },
    {
      "pokemonName": "チルット",
      "releaseDate": "2023-07-16T16:00:00Z",
      "rarity": 3,
      "sleepFaceName": "わたぐも寝",
      "energy": 110779,
      "ID": 159,
      "np": 7144000,
      "expCandy": 7,
      "researchExp": 346,
      "dreamShard": 726
    },
    {
      "pokemonName": "カメール",
      "releaseDate": "2023-07-16T16:00:00Z",
      "rarity": 2,
      "sleepFaceName": "こもらない寝",
      "energy": 203429,
      "ID": 38,
      "np": 7714000,
      "expCandy": 7,
      "researchExp": 327,
      "dreamShard": 686
    },
    {
      "pokemonName": "リオル",
      "releaseDate": "2023-07-16T16:00:00Z",
      "rarity": 3,
      "sleepFaceName": "かたひざたて寝",
      "energy": 203429,
      "ID": 300,
      "np": 8322000,
      "expCandy": 7,
      "researchExp": 402,
      "dreamShard": 843
    },
    {
      "pokemonName": "ドードー",
      "releaseDate": "2023-07-16T16:00:00Z",
      "rarity": 4,
      "sleepFaceName": "おなかのうえ寝",
      "energy": 151061,
      "ID": 364,
      "np": 9120000,
      "expCandy": 8,
      "researchExp": 397,
      "dreamShard": 1181
    },
    {
      "pokemonName": "ピチュー",
      "releaseDate": "2023-07-16T16:00:00Z",
      "rarity": 4,
      "sleepFaceName": "おなかのうえ寝",
      "energy": 151061,
      "ID": 388,
      "np": 9120000,
      "expCandy": 8,
      "researchExp": 397,
      "dreamShard": 1181
    },
    {
      "pokemonName": "ププリン",
      "releaseDate": "2023-07-16T16:00:00Z",
      "rarity": 4,
      "sleepFaceName": "おなかのうえ寝",
      "energy": 151061,
      "ID": 389,
      "np": 9120000,
      "expCandy": 8,
      "researchExp": 660,
      "dreamShard": 712
    },
    {
      "pokemonName": "ソーナノ",
      "releaseDate": "2023-07-16T16:00:00Z",
      "rarity": 4,
      "sleepFaceName": "おなかのうえ寝",
      "energy": 151061,
      "ID": 415,
      "np": 9120000,
      "expCandy": 8,
      "researchExp": 660,
      "dreamShard": 712
    },
    {
      "pokemonName": "トゲピー",
      "releaseDate": "2023-07-16T16:00:00Z",
      "rarity": 3,
      "sleepFaceName": "カラのなか寝",
      "energy": 110779,
      "ID": 69,
      "np": 9918000,
      "expCandy": 7,
      "researchExp": 479,
      "dreamShard": 1005
    },
    {
      "pokemonName": "ゼニガメ",
      "releaseDate": "2023-07-16T16:00:00Z",
      "rarity": 3,
      "sleepFaceName": "ひっくりかえり寝",
      "energy": 151061,
      "ID": 36,
      "np": 9918000,
      "expCandy": 7,
      "researchExp": 479,
      "dreamShard": 1005
    },
    {
      "pokemonName": "チルット",
      "releaseDate": "2023-07-16T16:00:00Z",
      "rarity": 4,
      "sleepFaceName": "おなかのうえ寝",
      "energy": 151061,
      "ID": 412,
      "np": 9918000,
      "expCandy": 8,
      "researchExp": 530,
      "dreamShard": 1114
    },
    {
      "pokemonName": "ピィ",
      "releaseDate": "2023-09-27T20:00:00Z",
      "rarity": 3,
      "sleepFaceName": "ひっくりかえり寝",
      "energy": 151061,
      "ID": 438,
      "np": 9918000,
      "expCandy": 7,
      "researchExp": 649,
      "dreamShard": 700
    },
    {
      "pokemonName": "ウソッキー",
      "releaseDate": "2023-07-16T16:00:00Z",
      "rarity": 3,
      "sleepFaceName": "きのふりしない寝",
      "energy": 203429,
      "ID": 120,
      "np": 10830000,
      "expCandy": 8,
      "researchExp": 567,
      "dreamShard": 1014
    },
    {
      "pokemonName": "クワッス",
      "releaseDate": "2024-07-15T07:00:00Z",
      "rarity": 2,
      "sleepFaceName": "かみととのえ寝",
      "energy": 75531,
      "ID": 559,
      "np": 11780000,
      "expCandy": 5,
      "researchExp": 600,
      "dreamShard": 858
    },
    {
      "pokemonName": "ヌイコグマ",
      "releaseDate": "2024-01-24T07:00:00Z",
      "rarity": 2,
      "sleepFaceName": "ふんばり寝",
      "energy": 110779,
      "ID": 501,
      "np": 11780000,
      "expCandy": 5,
      "researchExp": 636,
      "dreamShard": 794
    },
    {
      "pokemonName": "リオル",
      "releaseDate": "2023-07-16T16:00:00Z",
      "rarity": 4,
      "sleepFaceName": "おなかのうえ寝",
      "energy": 151061,
      "ID": 420,
      "np": 11780000,
      "expCandy": 8,
      "researchExp": 629,
      "dreamShard": 1320
    },
    {
      "pokemonName": "ゼニガメ",
      "releaseDate": "2023-07-16T16:00:00Z",
      "rarity": 4,
      "sleepFaceName": "おなかのうえ寝",
      "energy": 151061,
      "ID": 334,
      "np": 13490000,
      "expCandy": 8,
      "researchExp": 720,
      "dreamShard": 1513
    },
    {
      "pokemonName": "トゲピー",
      "releaseDate": "2023-07-16T16:00:00Z",
      "rarity": 4,
      "sleepFaceName": "おなかのうえ寝",
      "energy": 151061,
      "ID": 390,
      "np": 13490000,
      "expCandy": 8,
      "researchExp": 720,
      "dreamShard": 1513
    },
    {
      "pokemonName": "ピィ",
      "releaseDate": "2023-09-27T20:00:00Z",
      "rarity": 4,
      "sleepFaceName": "おなかのうえ寝",
      "energy": 511595,
      "ID": 439,
      "np": 13490000,
      "expCandy": 8,
      "researchExp": 977,
      "dreamShard": 1053
    },
    {
      "pokemonName": "ウソッキー",
      "releaseDate": "2023-07-16T16:00:00Z",
      "rarity": 4,
      "sleepFaceName": "おなかのうえ寝",
      "energy": 511595,
      "ID": 395,
      "np": 14326000,
      "expCandy": 9,
      "researchExp": 831,
      "dreamShard": 1489
    },
    {
      "pokemonName": "カメックス",
      "releaseDate": "2023-07-16T16:00:00Z",
      "rarity": 1,
      "sleepFaceName": "からにこもる寝",
      "energy": 810696,
      "ID": 91,
      "np": 14326000,
      "expCandy": 8,
      "researchExp": 540,
      "dreamShard": 1134
    },
    {
      "pokemonName": "ドードリオ",
      "releaseDate": "2023-07-16T16:00:00Z",
      "rarity": 3,
      "sleepFaceName": "みつご寝",
      "energy": 810696,
      "ID": 201,
      "np": 15466000,
      "expCandy": 9,
      "researchExp": 663,
      "dreamShard": 1706
    },
    {
      "pokemonName": "ウェルカモ",
      "releaseDate": "2024-07-15T07:00:00Z",
      "rarity": 2,
      "sleepFaceName": "かみととのえ寝",
      "energy": 423979,
      "ID": 563,
      "np": 19570000,
      "expCandy": 7,
      "researchExp": 995,
      "dreamShard": 1421
    },
    {
      "pokemonName": "ヌイコグマ",
      "releaseDate": "2024-01-24T07:00:00Z",
      "rarity": 3,
      "sleepFaceName": "まるただき寝",
      "energy": 511595,
      "ID": 502,
      "np": 19570000,
      "expCandy": 7,
      "researchExp": 1204,
      "dreamShard": 1501
    },
    {
      "pokemonName": "キテルグマ",
      "releaseDate": "2024-01-24T07:00:00Z",
      "rarity": 2,
      "sleepFaceName": "ぼうだち寝",
      "energy": 810696,
      "ID": 505,
      "np": 19570000,
      "expCandy": 7,
      "researchExp": 1117,
      "dreamShard": 1202
    },
    {
      "pokemonName": "ドードリオ",
      "releaseDate": "2023-07-16T16:00:00Z",
      "rarity": 4,
      "sleepFaceName": "おなかのうえ寝",
      "energy": 342406,
      "ID": 365,
      "np": 20824000,
      "expCandy": 10,
      "researchExp": 988,
      "dreamShard": 2544
    },
    {
      "pokemonName": "カメール",
      "releaseDate": "2023-07-16T16:00:00Z",
      "rarity": 3,
      "sleepFaceName": "つっぷし寝",
      "energy": 704953,
      "ID": 39,
      "np": 22154000,
      "expCandy": 9,
      "researchExp": 1063,
      "dreamShard": 2234
    },
    {
      "pokemonName": "ヌイコグマ",
      "releaseDate": "2024-01-24T07:00:00Z",
      "rarity": 4,
      "sleepFaceName": "おなかのうえ寝",
      "energy": 511595,
      "ID": 503,
      "np": 25536000,
      "expCandy": 8,
      "researchExp": 1742,
      "dreamShard": 2171
    },
    {
      "pokemonName": "ウェーニバル",
      "releaseDate": "2024-07-15T07:00:00Z",
      "rarity": 1,
      "sleepFaceName": "かたひざたて寝",
      "energy": 1038306,
      "ID": 566,
      "np": 27132000,
      "expCandy": 8,
      "researchExp": 1230,
      "dreamShard": 1757
    },
    {
      "pokemonName": "カメール",
      "releaseDate": "2023-07-16T16:00:00Z",
      "rarity": 4,
      "sleepFaceName": "おなかのうえ寝",
      "energy": 266875,
      "ID": 335,
      "np": 28766000,
      "expCandy": 10,
      "researchExp": 1530,
      "dreamShard": 3216
    },
    {
      "pokemonName": "カメックス",
      "releaseDate": "2023-07-16T16:00:00Z",
      "rarity": 2,
      "sleepFaceName": "こもらない寝",
      "energy": 1289248,
      "ID": 92,
      "np": 28766000,
      "expCandy": 10,
      "researchExp": 1208,
      "dreamShard": 2538
    },
    {
      "pokemonName": "エルレイド",
      "releaseDate": "2024-01-24T07:00:00Z",
      "rarity": 1,
      "sleepFaceName": "れいぎただしい寝",
      "energy": 1289248,
      "ID": 496,
      "np": 31806000,
      "expCandy": 8,
      "researchExp": 1063,
      "dreamShard": 2736
    },
    {
      "pokemonName": "クワッス",
      "releaseDate": "2024-07-15T07:00:00Z",
      "rarity": 3,
      "sleepFaceName": "ぼさぼさ寝",
      "energy": 423979,
      "ID": 560,
      "np": 33478000,
      "expCandy": 7,
      "researchExp": 1940,
      "dreamShard": 2771
    },
    {
      "pokemonName": "クワッス",
      "releaseDate": "2024-07-15T07:00:00Z",
      "rarity": 4,
      "sleepFaceName": "おなかのうえ寝",
      "energy": 511595,
      "ID": 561,
      "np": 38304000,
      "expCandy": 8,
      "researchExp": 2462,
      "dreamShard": 3516
    },
    {
      "pokemonName": "スイクン",
      "releaseDate": "2024-09-02T07:00:00Z",
      "rarity": 1,
      "sleepFaceName": "ちからため寝",
      "energy": 1289248,
      "ID": 578,
      "np": 46208000,
      "expCandy": 10,
      "researchExp": 1054,
      "dreamShard": 4844
    },
    {
      "pokemonName": "キテルグマ",
      "releaseDate": "2024-01-24T07:00:00Z",
      "rarity": 3,
      "sleepFaceName": "まるただき寝",
      "energy": 1582395,
      "ID": 506,
      "np": 46208000,
      "expCandy": 9,
      "researchExp": 3005,
      "dreamShard": 3232
    },
    {
      "pokemonName": "ウェルカモ",
      "releaseDate": "2024-07-15T07:00:00Z",
      "rarity": 3,
      "sleepFaceName": "みだれがみ寝",
      "energy": 1038306,
      "ID": 564,
      "np": 52706000,
      "expCandy": 9,
      "researchExp": 3052,
      "dreamShard": 4358
    },
    {
      "pokemonName": "ウェーニバル",
      "releaseDate": "2024-07-15T07:00:00Z",
      "rarity": 2,
      "sleepFaceName": "きめポーズ寝",
      "energy": 1582395,
      "ID": 567,
      "np": 52706000,
      "expCandy": 10,
      "researchExp": 2671,
      "dreamShard": 3814
    },
    {
      "pokemonName": "キテルグマ",
      "releaseDate": "2024-01-24T07:00:00Z",
      "rarity": 4,
      "sleepFaceName": "おなかのうえ寝",
      "energy": 1741777,
      "ID": 507,
      "np": 55594000,
      "expCandy": 10,
      "researchExp": 4009,
      "dreamShard": 4311
    },
    {
      "pokemonName": "エルレイド",
      "releaseDate": "2024-01-24T07:00:00Z",
      "rarity": 2,
      "sleepFaceName": "いあいぎり寝",
      "energy": 1910321,
      "ID": 497,
      "np": 55594000,
      "expCandy": 10,
      "researchExp": 2076,
      "dreamShard": 5348
    },
    {
      "pokemonName": "カメックス",
      "releaseDate": "2023-07-16T16:00:00Z",
      "rarity": 3,
      "sleepFaceName": "ひっくりかえり寝",
      "energy": 2276921,
      "ID": 93,
      "np": 62776000,
      "expCandy": 12,
      "researchExp": 3005,
      "dreamShard": 6318
    },
    {
      "pokemonName": "ウェルカモ",
      "releaseDate": "2024-07-15T07:00:00Z",
      "rarity": 4,
      "sleepFaceName": "おなかのうえ寝",
      "energy": 1038306,
      "ID": 565,
      "np": 65702000,
      "expCandy": 10,
      "researchExp": 4220,
      "dreamShard": 6024
    },
    {
      "pokemonName": "カメックス",
      "releaseDate": "2023-07-16T16:00:00Z",
      "rarity": 4,
      "sleepFaceName": "おなかのうえ寝",
      "energy": 1431702,
      "ID": 336,
      "np": 77102000,
      "expCandy": 13,
      "researchExp": 4093,
      "dreamShard": 8605
    },
    {
      "pokemonName": "エルレイド",
      "releaseDate": "2024-01-24T07:00:00Z",
      "rarity": 3,
      "sleepFaceName": "ゆめでいあいぎり寝",
      "energy": 3143935,
      "ID": 498,
      "np": 115976000,
      "expCandy": 12,
      "researchExp": 4946,
      "dreamShard": 12745
    },
    {
      "pokemonName": "スイクン",
      "releaseDate": "2024-09-02T07:00:00Z",
      "rarity": 2,
      "sleepFaceName": "めいそう寝",
      "energy": 1910321,
      "ID": 579,
      "np": 130074000,
      "expCandy": 12,
      "researchExp": 5091,
      "dreamShard": 12084
    },
    {
      "pokemonName": "エルレイド",
      "releaseDate": "2024-01-24T07:00:00Z",
      "rarity": 4,
      "sleepFaceName": "おなかのうえ寝",
      "energy": 2088527,
      "ID": 499,
      "np": 139612000,
      "expCandy": 13,
      "researchExp": 6604,
      "dreamShard": 17017
    },
    {
      "pokemonName": "ウェーニバル",
      "releaseDate": "2024-07-15T07:00:00Z",
      "rarity": 3,
      "sleepFaceName": "ゆめでダンス寝",
      "energy": 2686523,
      "ID": 568,
      "np": 139612000,
      "expCandy": 12,
      "researchExp": 8079,
      "dreamShard": 11533
    },
    {
      "pokemonName": "ウェーニバル",
      "releaseDate": "2024-07-15T07:00:00Z",
      "rarity": 4,
      "sleepFaceName": "おなかのうえ寝",
      "energy": 1741777,
      "ID": 569,
      "np": 163742000,
      "expCandy": 13,
      "researchExp": 10516,
      "dreamShard": 15012
    },
    {
      "pokemonName": "スイクン",
      "releaseDate": "2024-09-02T07:00:00Z",
      "rarity": 3,
      "sleepFaceName": "きたかぜ寝",
      "energy": 3143935,
      "ID": 580,
      "np": 275196000,
      "expCandy": 14,
      "researchExp": 13303,
      "dreamShard": 27414
    }
  ]
]